Workbook

Sheet Instructions
A1: ShopBase Factor Rate Reduction Model: How to Use This File
A3: This model answers one question: should CapFlow reduce the ShopBase factor rate by 0.5%?
A5: The file has four tabs:
A6: 1. Instructions -- this page
A7: 2. Assumptions -- change the yellow cells to update the whole model
A8: 3. Current State -- ShopBase performance over the last 18 months
A9: 4. Scenarios -- three volume uplift scenarios and their revenue impact
A11: HOW TO USE IT
A13: Go to the Assumptions tab.
A14: The yellow cells are the only ones you need to change.
A15: All other cells contain formulas and will update automatically.
A17: The most important inputs are the three volume uplift assumptions.
... A31: before committing to a full rollout.

Sheet Assumptions
A1: Assumption | B1: Value | C1: Notes
A2: Rate cut | B2: 0.005 | C2: Factor rate reduction being tested
A3: Current avg factor rate | B3: 1.2371389 | C3: Average across ShopBase book
A4: Average deal size | B4: 14937.818 | C4: Average funded amount per deal
A5: Total deals (current) | B5: 1433 | C5: Total ShopBase deals in period
A6: Total funded volume | B6: 21405894 | C6: Total funded volume in period
A8: SCENARIO UPLIFTS (change these) | C8: These are the key assumptions -- adjust based on your judgement
A9: Conservative uplift | B9: 0.1 | C9: Low end: merchants are not very price sensitive
A10: Base uplift | B10: 0.2 | C10: Central case
A11: Optimistic uplift | B11: 0.35 | C11: High end: strong price sensitivity

Sheet Current State
A1: ShopBase Current State (18-month period) | B1: Value
A2: Total deals funded | B2: =Assumptions!B5
A3: Total funded volume | B3: =Assumptions!B6
A4: Average deal size | B4: =Assumptions!B4
A5: Average factor rate | B5: =Assumptions!B3
A7: Gross revenue (fees) | B7: 4457547.8
A8: Default losses | B8: 696079.57
A9: Net revenue | B9: =B7-B8
A11: Default rate | B11: 0.071179344
A12: Risk-adjusted return | B12: 0.17572115
A14: New factor rate (post cut) | B14: =Assumptions!B3-Assumptions!B2
A15: New margin per £1 | B15: =Assumptions!B3-Assumptions!B2-1
A16: Revenue lost on existing book | B16: =Assumptions!B6*Assumptions!B2
A17: Revenue per new deal | B17: =Assumptions!B4*(Assumptions!B3-Assumptions!B2-1)
A18: Breakeven new deals | B18: =B16/B17
A19: Breakeven uplift % | B19: =B18/Assumptions!B5

Sheet Scenarios
A1: Metric | B1: Conservative | C1: Base | D1: Optimistic
A2: Volume uplift assumed | B2: =Assumptions!B9 | C2: =Assumptions!B10 | D2: =Assumptions!B11
A3: New deals | B3: =ROUND(Assumptions!B5*Assumptions!B9,0) | C3: =ROUND(Assumptions!B5*Assumptions!B10,0) | D3: =ROUND(Assumptions!B5*Assumptions!B11,0)
A4: New funded volume | B4: =ROUND(Assumptions!B5*Assumptions!B9,0)*Assumptions!B4 | C4: =ROUND(Assumptions!B5*Assumptions!B10,0)*Assumptions!B4 | D4: =ROUND(Assumptions!B5*Assumptions!B11,0)*Assumptions!B4
A5: Revenue lost (margin cut on existing book) | B5: ='Current State'!B16 | C5: ='Current State'!B16 | D5: ='Current State'!B16
A6: Revenue gained (new deals) | B6: =ROUND(Assumptions!B5*Assumptions!B9,0)*Assumptions!B4*(Assumptions!B3-Assumptions!B2-1) | C6: =ROUND(Assumptions!B5*Assumptions!B10,0)*Assumptions!B4*(Assumptions!B3-Assumptions!B2-1) | D6: =ROUND(Assumptions!B5*Assumptions!B11,0)*Assumptions!B4*(Assumptions!B3-Assumptions!B2-1)
A7: Net revenue impact | B7: =ROUND(Assumptions!B5*Assumptions!B9,0)*Assumptions!B4*(Assumptions!B3-Assumptions!B2-1)-'Current State'!B16 | C7: =ROUND(Assumptions!B5*Assumptions!B10,0)*Assumptions!B4*(Assumptions!B3-Assumptions!B2-1)-'Current State'!B16 | D7: =ROUND(Assumptions!B5*Assumptions!B11,0)*Assumptions!B4*(Assumptions!B3-Assumptions!B2-1)-'Current State'!B16
A8: NPV positive? | B8: =IF(ROUND(Assumptions!B5*Assumptions!B9,0)*Assumptions!B4*(Assumptions!B3-Assumptions!B2-1)-'Current State'!B16>0,"YES","NO") | C8: =IF(ROUND(Assumptions!B5*Assumptions!B10,0)*Assumptions!B4*(Assumptions!B3-Assumptions!B2-1)-'Current State'!B16>0,"YES","NO") | D8: =IF(ROUND(Assumptions!B5*Assumptions!B11,0)*Assumptions!B4*(Assumptions!B3-Assumptions!B2-1)-'Current State'!B16>0,"YES","NO")
A11: Breakeven uplift (from Current State tab): | B11: ='Current State'!B19
A12: The rate cut is NPV-positive above this threshold.
